MyArwReader/__init__.py
MyArwReader/metadata.py
MyArwReader/reader.py
MyArwReader/utils.py
myarwreader-0.1.2.dist-info/METADATA
myarwreader-0.1.2.dist-info/WHEEL
myarwreader-0.1.2.dist-info/top_level.txt
myarwreader-0.1.2.dist-info/RECORD
