Metadata-Version: 2.2
Name: MyArwReader
Version: 0.1.2
Summary: A lightweight package to read metadata from Sony .ARW files
Author: ARWEnthusiast
License: MIT
Requires-Python: >=3.6
Requires-Dist: pyexiftool
Dynamic: author
Dynamic: description
Dynamic: description-content-type
Dynamic: license
Dynamic: requires-dist
Dynamic: requires-python
Dynamic: summary
